flask_github_signature/__init__.py
flask_github_signature-0.1.1.dist-info/LICENSE
flask_github_signature-0.1.1.dist-info/METADATA
flask_github_signature-0.1.1.dist-info/WHEEL
flask_github_signature-0.1.1.dist-info/top_level.txt
flask_github_signature-0.1.1.dist-info/RECORD
