Metadata-Version: 2.1
Name: flask-github-signature
Version: 0.1.1
Summary: A Flask view decorator to verify Github's webhook signatures
Home-page: https://github.com/pabluk/flask-github-signature
Author: Pablo Seminario
Author-email: pablo@seminar.io
License: GNU General Public License v3 (GPLv3)
Project-URL: Bug Reports, https://github.com/pabluk/flask-github-signature/issues
Project-URL: Source, https://github.com/pabluk/flask-github-signature/issues
Project-URL: Documentation, https://github.com/pabluk/flask-github-signature#usage
Keywords: flask,decorator,github,webhook
Classifier: Development Status :: 4 - Beta
Classifier: Framework :: Flask
Classifier: Intended Audience :: Developers
Classifier: License :: OSI Approved :: GNU General Public License v3 (GPLv3)
Classifier: Operating System :: OS Independent
Classifier: Programming Language :: Python :: 3
Classifier: Programming Language :: Python :: 3.7
Classifier: Programming Language :: Python :: 3.8
Classifier: Programming Language :: Python :: 3.9
Classifier: Programming Language :: Python :: 3.10
Classifier: Programming Language :: Python :: 3.11
Classifier: Topic :: Software Development :: Libraries
License-File: LICENSE
